AUTHORS.rst
CHANGELOG.rst
CONTRIBUTING.rst
DEVELOPMENT.md
FILE_DESCRIPTIONS.md
LICENSE
MANIFEST.in
README.rst
get_parameters.py
setup.cfg
setup.py
tox.ini
docs/authors.rst
docs/changelog.rst
docs/conf.py
docs/contributing.rst
docs/index.rst
docs/installation.rst
docs/readme.rst
docs/requirements.txt
docs/spelling_wordlist.txt
docs/usage.rst
docs/reference/cfn-environment-base.rst
docs/reference/index.rst
src/cfn_environment_base.egg-info/PKG-INFO
src/cfn_environment_base.egg-info/SOURCES.txt
src/cfn_environment_base.egg-info/dependency_links.txt
src/cfn_environment_base.egg-info/entry_points.txt
src/cfn_environment_base.egg-info/requires.txt
src/cfn_environment_base.egg-info/top_level.txt
src/cfn_environment_base.egg-info/zip-safe
src/environmentbase/__init__.py
src/environmentbase/__main__.py
src/environmentbase/cli.py
src/environmentbase/environmentbase.py
src/environmentbase/monitor.py
src/environmentbase/networkbase.py
src/environmentbase/resources.py
src/environmentbase/template.py
src/environmentbase/utility.py
src/environmentbase/version.py
src/environmentbase/data/ami_cache.json
src/environmentbase/data/common_strings.json
src/environmentbase/data/config.json
src/environmentbase/data/config_schema.json
src/environmentbase/data/instance_type_2_arch.json
src/environmentbase/data/logging_bucket_policy.json
src/environmentbase/data/nat_takeover.sh
src/environmentbase/data/ntp_takeover.sh
src/environmentbase/data/region_arch_2_ami.json
src/environmentbase/patterns/__init__.py
src/environmentbase/patterns/base_network.py
src/environmentbase/patterns/bastion.py
src/environmentbase/patterns/cloudfront.py
src/environmentbase/patterns/ha_cluster.py
src/environmentbase/patterns/ha_nat.py
src/environmentbase/patterns/rds.py
src/environmentbase/scripts/awsbootstrap.py
src/environmentbase/scripts/environmentutil.py
src/environmentbase/scripts/instance_type_scraper.py
src/environmentbase/scripts/region_arch_2_ami.py
src/examples/__init__.py
src/examples/base_network.py
src/examples/basic.py
src/examples/child_stack.py
src/examples/nested_child_stack.py
src/tests/__init__.py
src/tests/test_environmentbase.py
src/tests/test_template.py
src/tests/resources/amzn_linux_ec2.json