Metadata-Version: 1.1
Name: cfn-environment-base
Version: 0.9.18
Summary: Base environment for Troposphere based CFN project environments
Home-page: https://github.com/ion-channel/cloudformation-environmentbase
Author: Patrick McClory, Patrick Pierson
Author-email: patrick@dualspark.com, patrick.pierson@ionchannel.io
License: ISC
Platform: UNKNOWN
Classifier: Development Status :: 4 - Beta
Classifier: Intended Audience :: Developers
Classifier: Operating System :: Unix
Classifier: Operating System :: POSIX
Classifier: Operating System :: Microsoft :: Windows
Classifier: Programming Language :: Python
Classifier: Programming Language :: Python :: 2.6
Classifier: Programming Language :: Python :: 2.7
Classifier: Programming Language :: Python :: 3
Classifier: Programming Language :: Python :: 3.3
Classifier: Programming Language :: Python :: 3.4
Classifier: Programming Language :: Python :: Implementation :: CPython
Classifier: Programming Language :: Python :: Implementation :: PyPy
Classifier: Topic :: Utilities
Classifier: Topic :: Software Development :: Code Generators
